fmft/__init__.py
fmft/formset_tables.py
fmft/views.py
fmft/templates/fmft/filter_form.html
fmft/templates/fmft/filtered_formset.html
fmft/templates/fmft/filtered_formset_table.html
fmft/templates/fmft/filtered_table.html
fmft/templates/fmft/form_field.html
fmft/templates/fmft/form_fields.html
fmft/templates/fmft/form_non_field_errors_tr.html
fmft/templates/fmft/formset_table.html
fmft/templates/fmft/tabular_formset.html
django_fmft-0.3.3.dist-info/LICENSE
django_fmft-0.3.3.dist-info/METADATA
django_fmft-0.3.3.dist-info/WHEEL
django_fmft-0.3.3.dist-info/entry_points.txt
django_fmft-0.3.3.dist-info/top_level.txt
django_fmft-0.3.3.dist-info/RECORD
