Metadata-Version: 2.1
Name: django_fmft
Version: 0.3.3
Summary: Class-based Views that integrate django-filters and django-tables2 with model formsets.
Author-email: Joseph Fall <powderflask@gmail.com>
License: MIT License
Project-URL: Homepage, https://github.com/powderflask/django-fmft
Project-URL: Repository, https://github.com/powderflask/django-fmft
Keywords: django_fmft,Django Filtered Model Formset,Tabular Class-based Views,django-filter,django-tables2,django-extra-views
Classifier: Development Status :: 4 - Beta
Classifier: License :: OSI Approved :: MIT License
Classifier: Intended Audience :: Developers
Classifier: Natural Language :: English
Classifier: Programming Language :: Python :: 3
Classifier: Framework :: Django
Requires-Python: <4.0,>=3.8
License-File: LICENSE
Requires-Dist: django
Requires-Dist: django-filter
Requires-Dist: django-tables2
Requires-Dist: django-extra-views
Provides-Extra: docs
Requires-Dist: sphinx ; extra == 'docs'
Requires-Dist: sphinx-rtd-theme ; extra == 'docs'
Requires-Dist: myst-parser ; extra == 'docs'
Requires-Dist: sphinxcontrib-django ; extra == 'docs'
Provides-Extra: style
Requires-Dist: black ; extra == 'style'
Requires-Dist: isort ; extra == 'style'
Requires-Dist: flake8 ; extra == 'style'
Requires-Dist: flake8-bugbear ; extra == 'style'
Provides-Extra: test
Requires-Dist: tox ; extra == 'test'
Requires-Dist: pytest ; extra == 'test'
Requires-Dist: pytest-django ; extra == 'test'
Requires-Dist: pytest-cov ; extra == 'test'
Requires-Dist: pytest-sugar ; extra == 'test'
Provides-Extra: utils
Requires-Dist: invoke ; extra == 'utils'
Requires-Dist: bumpver ; extra == 'utils'
Requires-Dist: build ; extra == 'utils'
Requires-Dist: twine ; extra == 'utils'
Requires-Dist: pip-tools ; extra == 'utils'
